{
  "events": [
    {
      "timestamp": "2026-04-08 09:48:39 ET",
      "type": "field_odds_refresh",
      "event_name": "Masters Tournament",
      "details": "Field updated: 14"
    },
    {
      "timestamp": "2026-04-08 03:45:59 ET",
      "type": "field_odds_refresh",
      "event_name": "Masters Tournament",
      "details": "Field updated: 14"
    },
    {
      "timestamp": "2026-04-07 15:15:25 ET",
      "type": "field_odds_refresh",
      "event_name": "Masters Tournament",
      "details": "Field updated: 14"
    },
    {
      "timestamp": "2026-04-07 09:46:13 ET",
      "type": "field_odds_refresh",
      "event_name": "Masters Tournament",
      "details": "Field updated: 14"
    },
    {
      "timestamp": "2026-04-07 03:42:22 ET",
      "type": "field_odds_refresh",
      "event_name": "Masters Tournament",
      "details": "Field updated: 14"
    },
    {
      "timestamp": "2026-04-06 16:28:21 ET",
      "type": "approach_refresh",
      "event_name": "",
      "details": "Approach skill refreshed \u2014 1,023 rows (l12/l24/ytd)"
    },
    {
      "timestamp": "2026-04-06 16:28:20 ET",
      "type": "rounds_refresh",
      "event_name": "",
      "details": "Rounds refreshed \u2014 10,208 rows across 29 events. Finishes rebuilt."
    },
    {
      "timestamp": "2026-04-06 16:28:15 ET",
      "type": "field_odds_refresh",
      "event_name": "Masters Tournament",
      "details": "Field updated: 14"
    },
    {
      "timestamp": "2026-04-06 15:11:51 ET",
      "type": "field_odds_refresh",
      "event_name": "Masters Tournament",
      "details": "Field updated: 14"
    },
    {
      "timestamp": "2026-04-06 12:35:24 ET",
      "type": "approach_refresh",
      "event_name": "",
      "details": "Approach skill refreshed \u2014 1,023 rows (l12/l24/ytd)"
    },
    {
      "timestamp": "2026-04-06 12:35:23 ET",
      "type": "rounds_refresh",
      "event_name": "",
      "details": "Rounds refreshed \u2014 10,208 rows across 29 events. Finishes rebuilt."
    },
    {
      "timestamp": "2026-04-06 12:35:18 ET",
      "type": "field_odds_refresh",
      "event_name": "Masters Tournament",
      "details": "Field updated: 14"
    },
    {
      "timestamp": "2026-04-06 09:24:59 ET",
      "type": "field_odds_refresh",
      "event_name": "Masters Tournament",
      "details": "Field updated: 14"
    },
    {
      "timestamp": "2026-04-06 08:44:53 ET",
      "type": "approach_refresh",
      "event_name": "",
      "details": "Approach skill refreshed \u2014 1,023 rows (l12/l24/ytd)"
    },
    {
      "timestamp": "2026-04-06 08:44:51 ET",
      "type": "rounds_refresh",
      "event_name": "",
      "details": "Rounds refreshed \u2014 10,208 rows across 29 events. Finishes rebuilt."
    },
    {
      "timestamp": "2026-04-06 08:44:47 ET",
      "type": "field_odds_refresh",
      "event_name": "Masters Tournament",
      "details": "Field updated: 14"
    },
    {
      "timestamp": "2026-04-06 03:55:16 ET",
      "type": "field_odds_refresh",
      "event_name": "Masters Tournament",
      "details": "Field updated: 14"
    },
    {
      "timestamp": "2026-04-05 14:55:38 ET",
      "type": "field_odds_refresh",
      "event_name": "Valero Texas Open",
      "details": "Field updated: 41, 14"
    },
    {
      "timestamp": "2026-04-05 09:12:45 ET",
      "type": "field_odds_refresh",
      "event_name": "Valero Texas Open",
      "details": "Field updated: 41, 14"
    },
    {
      "timestamp": "2026-04-05 03:17:21 ET",
      "type": "field_odds_refresh",
      "event_name": "Valero Texas Open",
      "details": "Field updated: 41, 14"
    }
  ]
}